fracsuite/__init__.py
fracsuite/__main__.py
fracsuite/acc.py
fracsuite/anisotropy.py
fracsuite/callbacks.py
fracsuite/config.py
fracsuite/general.py
fracsuite/helpers.py
fracsuite/highspeedimg.py
fracsuite/layer.py
fracsuite/nominals.py
fracsuite/over_nrg.py
fracsuite/scalp.py
fracsuite/simulate.py
fracsuite/simulate_future.py
fracsuite/specimen.py
fracsuite/splinters.py
fracsuite/state.py
fracsuite/test_prep.py
fracsuite/tester.py
fracsuite/tools.py
fracsuite/acceleration/__init__.py
fracsuite/acceleration/__main__.py
fracsuite/core/LinearestInterpolator.py
fracsuite/core/ProgWrapper.py
fracsuite/core/accelerationdata.py
fracsuite/core/anisotropy_images.py
fracsuite/core/arrays.py
fracsuite/core/calculate.py
fracsuite/core/coloring.py
fracsuite/core/contours.py
fracsuite/core/cracks.py
fracsuite/core/dataplotter.py
fracsuite/core/detection.py
fracsuite/core/geometry.py
fracsuite/core/image.py
fracsuite/core/imageplotting.py
fracsuite/core/imageprocessing.py
fracsuite/core/kernels.py
fracsuite/core/logging.py
fracsuite/core/mechanics.py
fracsuite/core/model_layers.py
fracsuite/core/navid_results.py
fracsuite/core/outputtable.py
fracsuite/core/plotting.py
fracsuite/core/point_process.py
fracsuite/core/preps.py
fracsuite/core/progress.py
fracsuite/core/pythontools.py
fracsuite/core/region.py
fracsuite/core/seel_prediction_data.py
fracsuite/core/series.py
fracsuite/core/signal.py
fracsuite/core/simulation.py
fracsuite/core/specimen.py
fracsuite/core/specimenprops.py
fracsuite/core/specimenregion.py
fracsuite/core/splinter.py
fracsuite/core/splinter_props.py
fracsuite/core/stochastics.py
fracsuite/core/stress.py
fracsuite/core/vectors.py
fracsuite/core/virtualspecimen.py
fracsuite/highspeed/__init__.py
fracsuite/highspeed/__main__.py
fracsuite/identifier/__init__.py
fracsuite/identifier/__main__.py
fracsuite/identifier/barcode.py
fracsuite/identifier/creator.py
fracsuite/organize/__init__.py
fracsuite/organize/__main__.py
fracsuite/scalper/__init__.py
fracsuite-1.1.0.dist-info/METADATA
fracsuite-1.1.0.dist-info/WHEEL
fracsuite-1.1.0.dist-info/entry_points.txt
fracsuite-1.1.0.dist-info/top_level.txt
fracsuite-1.1.0.dist-info/RECORD
