Metadata-Version: 2.1
Name: fracsuite
Version: 1.1.0
Summary: Package to help analyze fracture patterns on broken glass plys.
Author-email: Leon Bohmann <mail@leonbohmann.de>
Project-URL: Homepage, https://github.com/leonbohmann/fracture-suite
Project-URL: Bug Tracker, https://github.com/leonbohmann/fracture-suite/issues
Classifier: Programming Language :: Python :: 3
Classifier: License :: OSI Approved :: MIT License
Classifier: Operating System :: OS Independent
Requires-Python: >=3.7
Requires-Dist: matplotlib
Requires-Dist: opencv-python
Requires-Dist: numpy
Requires-Dist: tqdm
Requires-Dist: scikit-image
Requires-Dist: rich
Requires-Dist: scipy
Requires-Dist: apread
Requires-Dist: Pillow
Requires-Dist: reportlab
Requires-Dist: pylibdmtx
Requires-Dist: typer
Requires-Dist: openpyxl
Requires-Dist: xlsxwriter
Requires-Dist: scienceplots
Requires-Dist: deprecated
Requires-Dist: spazial ==0.1.11
Requires-Dist: splintaz ==0.1.5
